ploonetide/__init__.py
ploonetide/forecaster/__init__.py
ploonetide/forecaster/fitting_parameters.h5
ploonetide/forecaster/mr_forecast.py
ploonetide/numerical/simulator.py
ploonetide/odes/planet_moon.py
ploonetide/odes/star_planet.py
ploonetide/ploonetide.py
ploonetide/tests/test_codestyle.py
ploonetide/utils/__init__.py
ploonetide/utils/constants.py
ploonetide/utils/functions.py
ploonetide/version.py
ploonetide-1.0.3.dist-info/AUTHORS.rst
ploonetide-1.0.3.dist-info/LICENSE
ploonetide-1.0.3.dist-info/METADATA
ploonetide-1.0.3.dist-info/WHEEL
ploonetide-1.0.3.dist-info/RECORD
