Metadata-Version: 2.3
Name: ploonetide
Version: 1.0.3
Summary: Calculate tidal interactions in planetary systems
License: LICENSE
Keywords: Tidal,Simulation,TESS,Astronomy
Author: Jaime A. Alvarado-Montes
Author-email: rasjaime@gmail.com
Requires-Python: >=3.10
Classifier: Development Status :: 1 - Planning
Classifier: Intended Audience :: Science/Research
Classifier: License :: OSI Approved :: MIT License
Classifier: License :: Other/Proprietary License
Classifier: Operating System :: OS Independent
Classifier: Programming Language :: Python
Classifier: Programming Language :: Python :: 3
Classifier: Programming Language :: Python :: 3.10
Classifier: Programming Language :: Python :: 3.11
Classifier: Programming Language :: Python :: 3.12
Classifier: Programming Language :: Python :: 3.13
Classifier: Topic :: Scientific/Engineering :: Astronomy
Provides-Extra: dev
Provides-Extra: docs
Provides-Extra: gui
Provides-Extra: notebooks
Provides-Extra: viz
Requires-Dist: PyQt5 (>=5.15.11) ; extra == "gui" or extra == "dev"
Requires-Dist: argparse (>=1.0)
Requires-Dist: astroplan (>=0.7)
Requires-Dist: astropy (>=5.0)
Requires-Dist: astroquery (>=0.3.9)
Requires-Dist: beautifulsoup4 (>=1.0) ; extra == "viz" or extra == "dev"
Requires-Dist: h5py (>=1.0)
Requires-Dist: ipympl (>=0.9.7) ; extra == "notebooks" or extra == "dev"
Requires-Dist: ipython (>=1.0) ; extra == "notebooks" or extra == "dev"
Requires-Dist: ipywidgets (>=1.0) ; extra == "notebooks" or extra == "dev"
Requires-Dist: jupyterlab (>=1.0) ; extra == "notebooks" or extra == "dev"
Requires-Dist: matplotlib (>=1.5.3)
Requires-Dist: mechanicalsoup (>=1.0)
Requires-Dist: natsort (>=1.0)
Requires-Dist: numpy (>=1.18)
Requires-Dist: numpydoc (>=1.1.0) ; extra == "docs" or extra == "dev"
Requires-Dist: pandas (>=1.1.4)
Requires-Dist: pydata-sphinx-theme (>=0.7.1) ; extra == "docs" or extra == "dev"
Requires-Dist: pyfiglet (>=0.7.6)
Requires-Dist: scipy (>=0.19.0)
Requires-Dist: seaborn (>=0.11.2) ; extra == "viz" or extra == "dev"
Requires-Dist: sphinx-automodapi (>=0.13) ; extra == "docs" or extra == "dev"
Requires-Dist: sphinxcontrib-rawfiles (>=0.1.1) ; extra == "docs" or extra == "dev"
Requires-Dist: sphinxcontrib-restbuilder (>=0.2) ; extra == "docs" or extra == "dev"
Requires-Dist: tqdm (>=4.25.0)
Requires-Dist: uncertainties (>=1.0)
Project-URL: Bug Tracker, https://github.com/JAAlvarado-Montes/ploonetide/issues
Project-URL: Repository, https://github.com/JAAlvarado-Montes/ploonetide
